{
  "page_number": 452,
  "extraction": {
    "method": "digital",
    "engine": "PyMuPDF",
    "confidence_score": 0.9425,
    "correction_applied": false,
    "numeric_validation_passed": false
  },
  "content_blocks": [
    {
      "block_id": 1,
      "type": "paragraph",
      "language": "en",
      "text": "418 \nchapter 13\nCode Kitchen\nThis part’5 optional. We’re making the full BeatBox, GUI \nand all. In the Saving Objects chapter, we’11 learn how to \nsave and restore drum patterns. Finally, in the networking \nchapter (Make a Connection), we’11 turn the BeatBox into a \nworking chat client.\nCode Kitchen",
      "confidence": 0.95
    }
  ],
  "tables": [],
  "images": [
    {
      "image_id": 1,
      "type": "photo",
      "detected_text": "",
      "description": "A photograph or image (559x399)",
      "confidence": 0.6
    },
    {
      "image_id": 2,
      "type": "photo",
      "detected_text": "",
      "description": "A photograph or image (122x204)",
      "confidence": 0.6
    },
    {
      "image_id": 3,
      "type": "photo",
      "detected_text": "",
      "description": "A photograph or image (78x81)",
      "confidence": 0.6
    },
    {
      "image_id": 4,
      "type": "photo",
      "detected_text": "",
      "description": "A photograph or image (82x82)",
      "confidence": 0.6
    },
    {
      "image_id": 5,
      "type": "photo",
      "detected_text": "",
      "description": "A photograph or image (76x95)",
      "confidence": 0.6
    },
    {
      "image_id": 6,
      "type": "photo",
      "detected_text": "",
      "description": "A photograph or image (72x95)",
      "confidence": 0.6
    },
    {
      "image_id": 7,
      "type": "photo",
      "detected_text": "",
      "description": "A photograph or image (71x82)",
      "confidence": 0.6
    }
  ],
  "full_text": "418 \nchapter 13\nCode Kitchen\nThis part’5 optional. We’re making the full BeatBox, GUI \nand all. In the Saving Objects chapter, we’11 learn how to \nsave and restore drum patterns. Finally, in the networking \nchapter (Make a Connection), we’11 turn the BeatBox into a \nworking chat client.\nCode Kitchen",
  "source_image_path": "",
  "verified": false,
  "domain": "unknown",
  "confidence_tier": "silver",
  "decisions": [
    {
      "page": 452,
      "keyword": "PIPELINE_STEP",
      "detail": "type_detection: digital",
      "severity": "info"
    },
    {
      "page": 452,
      "keyword": "PIPELINE_STEP",
      "detail": "digital_extraction: 301 chars",
      "severity": "info"
    },
    {
      "page": 452,
      "keyword": "PIPELINE_STEP",
      "detail": "images_extracted: 7",
      "severity": "info"
    },
    {
      "page": 452,
      "keyword": "FINAL_ENGINE",
      "detail": "method=digital, engine=PyMuPDF",
      "severity": "info"
    }
  ]
}