{
  "page_number": 9,
  "extraction": {
    "method": "digital",
    "engine": "PyMuPDF",
    "confidence_score": 0.9425,
    "correction_applied": false,
    "numeric_validation_passed": true
  },
  "content_blocks": [
    {
      "block_id": 1,
      "type": "paragraph",
      "language": "en",
      "text": "To our brains, for always being there\n(despite shaky evidence)",
      "confidence": 0.95
    }
  ],
  "tables": [],
  "images": [],
  "full_text": "To our brains, for always being there\n(despite shaky evidence)",
  "source_image_path": "",
  "verified": false,
  "domain": "unknown",
  "confidence_tier": "silver",
  "decisions": [
    {
      "page": 9,
      "keyword": "PIPELINE_STEP",
      "detail": "type_detection: digital",
      "severity": "info"
    },
    {
      "page": 9,
      "keyword": "PIPELINE_STEP",
      "detail": "digital_extraction: 63 chars",
      "severity": "info"
    },
    {
      "page": 9,
      "keyword": "FINAL_ENGINE",
      "detail": "method=digital, engine=PyMuPDF",
      "severity": "info"
    }
  ]
}