{
  "page_number": 24,
  "extraction": {
    "method": "digital",
    "engine": "PyMuPDF",
    "confidence_score": 0.925,
    "correction_applied": false,
    "numeric_validation_passed": false
  },
  "content_blocks": [
    {
      "block_id": 1,
      "type": "paragraph",
      "language": "en",
      "text": "25. \nSee, for example, the recent Bletchley Declaration stemming from the AI Summit in the UK, https://www.gov.uk/\ngovernment/publications/ai-safety-summit-2023-the-bletchley-declaration/the-bletchley-declaration-by-countries-\nattending-the-ai-safety-summit-1-2-november-2023.\n26. \nScience Based Targets, “Corporate climate action accelerated in 2022, with an 87% increase in companies setting \nscience-based targets”, 17 August 2023, https://sciencebasedtargets.org/news/corporate-climate-action-accelerated-\nin-2022-with-an-87-increase-in-companies-setting-science-based-targets#:~:text=Companies%20representing%20mo-\nre%20than%20a,and%2042%25%20of%205%26P%20companies.\n27. \nLondon School of Economics, “What are the extent and causes of biodiversity 1055?”, 2 December 2022, \nhttps://www.lse.ac.uk/granthaminstitute/explainers/what-are-the-extent-and-causes-of-biodiversity-1055/.\n28. \nScimex, “Expert Reaction: 1 in 5 people rely on wild species for income and food”, 8 July 2022, https://www.scimex.org/\nnewsfeed/expert-reaction-1-in-5-people-rely-on-wild-species-for-income-and-food#:~:text=%E2%80%9C70%25%20\nof%20the%20world’5%20poor,Emery.\n29. \nIEA, “Energy intensity”, https://www.iea.org/reports/sdg7-data-and-projections/energy-intensity.\n30. \nUNFCCC, “Long-term strategies portal”, https://unfccc.int/process/the-paris-agreement/long-term-strategies.\n31. \nMcKinsey & Company, “An affordable, reliable, competitive path to net zero”, 30 November 2023, https://www.mckinsey.\ncom/capabilities/sustainability/our-insights/an-affordable-reliable-competitive-path-to-net-zero#/.\n32. \nZhang, Yong-Zhen and Edward C. Holmes, “A Genomic Perspective on the Origin and Emergence of SARS-CoV-2”, \nCell, 16 April 2020, https://www.ncbi.nlm.nih.gov/pmc/articles/PMC7194821/#:~:text=With%20the%20help%20of%20\nDr,early%20on%20January%2011%2C%202020.\n33. \nTatar, Moosa, Jalal Montazeri Shoorekchali, et al., “COVID-19 vaccine inequality: A global perspective”, Journal of Global \nHealth, 14 October 2022, https://www.ncbi.nlm.nih.gov/pmc/articles/PMC9559176/#:~:text=The%20inequality%20\nin%20vaccines%20was,on%20December%207%2C%202021.\n34. \nORF, “Global contest for medical equipment amidst the COVID19 pandemic”, 20 May 2020, https://www.orfonline.org/\nexpert-speak/global-contest-for-medical-equipment-amidst-the-covid19-pandemic-66438/.\n35. \nCalculated as the sum of years of life lost (YLL) and years lost due to disability (YLD).\n36. \nWorld Health Organization “Malaria”, https://www.who.int/data/gho/data/themes/malaria.\n37. \nKFF, “The U.5. Government and the World Health Organization”, 22 May 2023, https://www.kff.org/coronavirus-\ncovid-19/fact-sheet/the-u-5-government-and-the-world-health-organization/#:~:text=The%20revised%20amount%20\nrepresents%20a,is%20set%20at%20%246.86%20billion.\n38. \nThe World Bank, “620 hosts Official Launch of The Pandemic Fund”, 13 November 2022, https://www.worldbank.org/\nen/news/press-release/2022/11/12/g20-hosts-official-launch-of-the-pandemic-fund.\n39. \nAfrica CDC, “Partnerships for African Vaccine Manufacturing (PAVM) Framework for Action”, 3 March 2022, \nhttps://africacdc.org/download/partnerships-for-african-vaccine-manufacturing-pavm-framework-for-action/.\n40. \nButchard, Patrick and Bukky Balogun, “What is the proposed WHO Pandemic Preparedness Treaty?”, House of \nCommons Library,14 December 2023, https://commonslibrary.parliament.uk/research-briefings/cbp-9550/. \n41. \nFor example, the EU has a series of initiatives calling for greater international cooperation here: “Global Partnerships in \nHealth: Details of cooperation agreements in the field of health research”, https://research-and-innovation.ec.europa.eu/\nresearch-area/health/global-partnerships-health_en.\n42. \nUS Department of State, “Global Coalition to Address Synthetic Drug Threats”, https://www.state.gov/globalcoalition/.\n43. \nBrassey, Jacqueline, Brad Herbig, Barbara Jeffery, and Drew Ungerman “Reframing employee health: Moving beyond \nburnout to holistic health”, McKinsey Health Institute, 2 November 2023, https://www.mckinsey.com/mhi/our-insights/\nreframing-employee-health-moving-beyond-burnout-to-holistic-health.\n44. \nMcKinsey Health Institute, “Aging with purpose: Why meaningful engagement with society matters”, October 23, 2023, \nhttps://www.mckinsey.com/mhi/our-insights/aging-with-purpose-why-meaningful-engagement-with-society-matters.\n45. \nSignificant cyberattacks defined as those with an estimated impact of greater than $1 million or involving over 1 million \nfiles leaked classified as significant.\n46. \nLewis, James Andrew, Zhanna L. Malekos Smith, and Eugenia Lostri, “The Hidden Costs of Cybercrime”, CSIS, 9 \nDecember 2020, https://www.csis.org/analysis/hidden-costs-cybercrime.\n47. \nCimpanu, Catalin, “A decade of hacking: The most notable cyber-security events of the 20105”, ZDNet, \n \nhttps://www.zdnet.com/article/a-decade-of-hacking-the-most-notable-cyber-security-events-of-the-20105/.\n48. \nIbid.\n49. \nArctic Wolf, “A Brief History of Cybercrime”, 16 November 2022, https://arcticwolf.com/resources/blog/decade-of-\ncybercrime/.\n50. \nCollier, Roger, “NHS ransomware attack spreads worldwide”, 5 June 2017, https://www.ncbi.nlm.nih.gov/pmc/articles/\nPMC5461132/.\n51. \nUNHCR, “Global Trends”, https://www.unhcr.org/global-trends.\nThe Global Cooperation Barometer 2024\n24",
      "confidence": 0.95
    }
  ],
  "tables": [],
  "images": [],
  "full_text": "25. \nSee, for example, the recent Bletchley Declaration stemming from the AI Summit in the UK, https://www.gov.uk/\ngovernment/publications/ai-safety-summit-2023-the-bletchley-declaration/the-bletchley-declaration-by-countries-\nattending-the-ai-safety-summit-1-2-november-2023.\n26. \nScience Based Targets, “Corporate climate action accelerated in 2022, with an 87% increase in companies setting \nscience-based targets”, 17 August 2023, https://sciencebasedtargets.org/news/corporate-climate-action-accelerated-\nin-2022-with-an-87-increase-in-companies-setting-science-based-targets#:~:text=Companies%20representing%20mo-\nre%20than%20a,and%2042%25%20of%205%26P%20companies.\n27. \nLondon School of Economics, “What are the extent and causes of biodiversity 1055?”, 2 December 2022, \nhttps://www.lse.ac.uk/granthaminstitute/explainers/what-are-the-extent-and-causes-of-biodiversity-1055/.\n28. \nScimex, “Expert Reaction: 1 in 5 people rely on wild species for income and food”, 8 July 2022, https://www.scimex.org/\nnewsfeed/expert-reaction-1-in-5-people-rely-on-wild-species-for-income-and-food#:~:text=%E2%80%9C70%25%20\nof%20the%20world’5%20poor,Emery.\n29. \nIEA, “Energy intensity”, https://www.iea.org/reports/sdg7-data-and-projections/energy-intensity.\n30. \nUNFCCC, “Long-term strategies portal”, https://unfccc.int/process/the-paris-agreement/long-term-strategies.\n31. \nMcKinsey & Company, “An affordable, reliable, competitive path to net zero”, 30 November 2023, https://www.mckinsey.\ncom/capabilities/sustainability/our-insights/an-affordable-reliable-competitive-path-to-net-zero#/.\n32. \nZhang, Yong-Zhen and Edward C. Holmes, “A Genomic Perspective on the Origin and Emergence of SARS-CoV-2”, \nCell, 16 April 2020, https://www.ncbi.nlm.nih.gov/pmc/articles/PMC7194821/#:~:text=With%20the%20help%20of%20\nDr,early%20on%20January%2011%2C%202020.\n33. \nTatar, Moosa, Jalal Montazeri Shoorekchali, et al., “COVID-19 vaccine inequality: A global perspective”, Journal of Global \nHealth, 14 October 2022, https://www.ncbi.nlm.nih.gov/pmc/articles/PMC9559176/#:~:text=The%20inequality%20\nin%20vaccines%20was,on%20December%207%2C%202021.\n34. \nORF, “Global contest for medical equipment amidst the COVID19 pandemic”, 20 May 2020, https://www.orfonline.org/\nexpert-speak/global-contest-for-medical-equipment-amidst-the-covid19-pandemic-66438/.\n35. \nCalculated as the sum of years of life lost (YLL) and years lost due to disability (YLD).\n36. \nWorld Health Organization “Malaria”, https://www.who.int/data/gho/data/themes/malaria.\n37. \nKFF, “The U.5. Government and the World Health Organization”, 22 May 2023, https://www.kff.org/coronavirus-\ncovid-19/fact-sheet/the-u-5-government-and-the-world-health-organization/#:~:text=The%20revised%20amount%20\nrepresents%20a,is%20set%20at%20%246.86%20billion.\n38. \nThe World Bank, “620 hosts Official Launch of The Pandemic Fund”, 13 November 2022, https://www.worldbank.org/\nen/news/press-release/2022/11/12/g20-hosts-official-launch-of-the-pandemic-fund.\n39. \nAfrica CDC, “Partnerships for African Vaccine Manufacturing (PAVM) Framework for Action”, 3 March 2022, \nhttps://africacdc.org/download/partnerships-for-african-vaccine-manufacturing-pavm-framework-for-action/.\n40. \nButchard, Patrick and Bukky Balogun, “What is the proposed WHO Pandemic Preparedness Treaty?”, House of \nCommons Library,14 December 2023, https://commonslibrary.parliament.uk/research-briefings/cbp-9550/. \n41. \nFor example, the EU has a series of initiatives calling for greater international cooperation here: “Global Partnerships in \nHealth: Details of cooperation agreements in the field of health research”, https://research-and-innovation.ec.europa.eu/\nresearch-area/health/global-partnerships-health_en.\n42. \nUS Department of State, “Global Coalition to Address Synthetic Drug Threats”, https://www.state.gov/globalcoalition/.\n43. \nBrassey, Jacqueline, Brad Herbig, Barbara Jeffery, and Drew Ungerman “Reframing employee health: Moving beyond \nburnout to holistic health”, McKinsey Health Institute, 2 November 2023, https://www.mckinsey.com/mhi/our-insights/\nreframing-employee-health-moving-beyond-burnout-to-holistic-health.\n44. \nMcKinsey Health Institute, “Aging with purpose: Why meaningful engagement with society matters”, October 23, 2023, \nhttps://www.mckinsey.com/mhi/our-insights/aging-with-purpose-why-meaningful-engagement-with-society-matters.\n45. \nSignificant cyberattacks defined as those with an estimated impact of greater than $1 million or involving over 1 million \nfiles leaked classified as significant.\n46. \nLewis, James Andrew, Zhanna L. Malekos Smith, and Eugenia Lostri, “The Hidden Costs of Cybercrime”, CSIS, 9 \nDecember 2020, https://www.csis.org/analysis/hidden-costs-cybercrime.\n47. \nCimpanu, Catalin, “A decade of hacking: The most notable cyber-security events of the 20105”, ZDNet, \n \nhttps://www.zdnet.com/article/a-decade-of-hacking-the-most-notable-cyber-security-events-of-the-20105/.\n48. \nIbid.\n49. \nArctic Wolf, “A Brief History of Cybercrime”, 16 November 2022, https://arcticwolf.com/resources/blog/decade-of-\ncybercrime/.\n50. \nCollier, Roger, “NHS ransomware attack spreads worldwide”, 5 June 2017, https://www.ncbi.nlm.nih.gov/pmc/articles/\nPMC5461132/.\n51. \nUNHCR, “Global Trends”, https://www.unhcr.org/global-trends.\nThe Global Cooperation Barometer 2024\n24",
  "source_image_path": "",
  "verified": false,
  "domain": "unknown",
  "confidence_tier": "silver",
  "decisions": [
    {
      "page": 24,
      "keyword": "PIPELINE_STEP",
      "detail": "type_detection: digital",
      "severity": "info"
    },
    {
      "page": 24,
      "keyword": "PIPELINE_STEP",
      "detail": "digital_extraction: 5329 chars",
      "severity": "info"
    },
    {
      "page": 24,
      "keyword": "FINAL_ENGINE",
      "detail": "method=digital, engine=PyMuPDF",
      "severity": "info"
    }
  ]
}